{
    "Objects" : [
        {
            "ObjectType" : "BaseBloodstain",
            "Name" : "Bloodstain",
            "Sprite" : "object-bloodstain.png",
            "Tint" : [ 1.0, 1.0, 1.0, 0.5 ],
            "Render Layer" : "Back",
            "Description" : "A pool of blood",
            "Saved" : false,
            "Display In Editor" : false
        },
        {
            "ObjectType" : "BaseChest",
            "Name" : "Small Chest",            
            "Description" : "A small wooden chest. It could contain various items.",
            "Display In Editor" : false
        },


        {
            "ObjectType" : "Bloodstain", 
            "Base" : "BaseBloodstain",
            "Random Rotation" : true
        },
        {
            "ObjectType" : "Bloodstain_Permanent", 
            "Base" : "BaseBloodstain",
            "Saved" : true,
            "Random Rotation" : true,
            "Display In Editor" : true
        },
        {
            "ObjectType" : "Bloodstain_Wall", 
            "Base" : "BaseBloodstain",
            "Sprite" : "object-bloodstain_wall.png"
        },
        {
            "ObjectType" : "Chest", 
            "Base" : "BaseChest",
            "Container" : { 
                "ItemsChance" : 100,
                "MaxItems" : 4
            },
            "Sprite" : "object-chest_closed.png",
            "Display In Editor" : true
        },
        {
            "ObjectType" : "Chest_Open", 
            "Base" : "BaseChest",
            "Name" : "Large Chest",  
            "Description" : "A large ornate chest. It could contain various items.",
            "Container" : {},
            "Sprite" : "object-chest_open.png",
            "Display In Editor" : true
        },
        {
            "ObjectType" : "Chest_Large", 
            "Base" : "BaseChest",
            "Name" : "Large Chest",  
            "Description" : "A large ornate chest. It could contain various items.",
            "Container" : { 
                "ItemsChance" : 100,
                "MaxItems" : 7
            },
            "Sprite" : "object-chestlarge_closed.png",
            "Display In Editor" : true
        },
        {
            "ObjectType" : "Chest_Large_Open", 
            "Base" : "BaseChest",
            "Container" : {},
            "Sprite" : "object-chestlarge_open.png",
            "Display In Editor" : true
        },
        {
            "Name" : "Loot",
            "ObjectType" : "Loot",
            "Container" : {},
            "Sprite" : "object-loot.png",
            "Description" : "Items strewn about the ground.",
            "Display In Editor" : false
        },
        {
            "Name" : "Wood Barrel",
            "ObjectType" : "Barrel",
            "Sprite" : "object-barrel_closed.png",
            "Container" : { 
                "ItemsChance" : 10,
                "MaxItems" : 1,
                "PossibleItems" : [
                    "meat", "berries", "fruit", "frond", "shovel", "plywoodshield", "pitchfork"   
				]
            },
            "Description" : "A wood barrel with metal rings. It could contain loot."
        },
        {
            "Name" : "Wood Barrel",
            "ObjectType" : "Barrel_Open",
            "Sprite" : "object-barrel_open.png",
            "Container" : {},
            "Description" : "A wood barrel with metal rings. It has been opened."
        },
        {
            "Name" : "Campfire",
            "ObjectType" : "Campfire",
            "Sprite" : "object-campfire.png",
            "Physics" : "Solid",
            "Light" : 4,
            "Description" : "A roaring fire."
        },
        {
            "Name" : "Small Table",
            "ObjectType" : "Table",
            "Sprite" : "object-table_small.png",
			"Path Cost" : 2,
            "Render Layer" : "Back",
            "Description" : "A crudely crafted wooden table."
        },
		{
            "Name" : "Table",
            "ObjectType" : "Table_Large",
            "Sprite" : "object-table_big.png",
			"Path Cost" : 2,
            "Render Layer" : "Back",
            "Description" : "A crudely crafted wooden table."
        },
		{
			"Name" : "Chair",
			"ObjectType" : "Chair_Right",
			"Sprite" : "object-chair_right.png",
			"Path Cost" : 2,
			"Render Layer" : "Back",
			"Description" : ""
		},
		{
			"Name" : "Chair",
			"ObjectType" : "Chair_Left",
			"Sprite" : "object-chair_left.png",
			"Path Cost" : 2,
			"Render Layer" : "Back",
			"Description" : ""
		},
        {
            "Name" : "Door",
            "ObjectType" : "Door_Closed",
            "Sprite" : "object-door_wood_closed.png",
            "Description" : "A wood door.",
			"Opaque" : true,
            "Path Cost" : 100,
            "OpenType" : "Door_Open"
        },
        {
            "Name" : "Door",
            "ObjectType" : "Door_Open",
            "Sprite" : "object-door_wood_open.png",
            "Description" : "A wood door, open."
        },
        {
            "Name" : "Prison Door",
            "ObjectType" : "Prison_Door_Closed",
            "Sprite" : "object-door_metal_closed.png",
            "Description" : "A steel door.",
			"Opaque" : true,
			"Pulse" : {
				"Receive" : true
			},
            "Path Cost" : 100,
            "Permissions" : [ "Can_Open_Prison_Cells" ],
            "OpenType" : "Prison_Door_Open"
        },
        {
            "Name" : "Prison Door",
            "ObjectType" : "Prison_Door_Open",
            "Sprite" : "object-door_metal_open.png",
			"LuaEvents" : [
                { "Event" : "OnPulseReceived", "Script" : "Core.Objects.Door_OnPulseReceived" }
			],
            "Description" : "A steel door.",
			"Pulse" : {
				"Receive" : true
			}
        },
        {
            "Name" : "Ensistic Door",
            "ObjectType" : "Ensis_Door_Closed",
            "Sprite" : "object-door_ensis_closed.png",
            "Description" : "A door only the Ensis can open.",
			"Opaque" : true,
			"Pulse" : {
				"Receive" : true
			},
			"Permissions" : [ "Can_Enter_Ensis" ],
            "Path Cost" : 100,
            "OpenType" : "Ensis_Door_Open"
        },
        {
            "Name" : "Ensistic Door",
            "ObjectType" : "Ensis_Door_Open",
            "Sprite" : "object-door_ensis_open.png",
			"LuaEvents" : [
                { "Event" : "OnPulseReceived", "Script" : "Core.Objects.Door_OnPulseReceived" }
			],
            "Description" : "A door only the Ensis can open.",
			"Pulse" : {
				"Receive" : true
			}
        },
        {
            "Name" : "Strange Door",
            "ObjectType" : "Magna_Door_Closed",
            "Sprite" : "object-door_magna_closed.png",
            "Description" : "A strange closed door.",
			"Opaque" : true,
			"Pulse" : {
				"Receive" : true
			},
			"Permissions" : [ "Can_Enter_Magna" ],
            "Path Cost" : 100,
            "OpenType" : "Magna_Door_Open"
        },
		{
            "Name" : "Strange Door",
            "ObjectType" : "Magna_Door_Open",
            "Sprite" : "object-door_magna_open.png",
			"LuaEvents" : [
                { "Event" : "OnPulseReceived", "Script" : "Core.Objects.Door_OnPulseReceived" }
			],
            "Description" : "A strange door. Open.",
			"Pulse" : {
				"Receive" : true
			}
        },
		{
			"Name" : "Magnetic Door",
			"ObjectType" : "Kin_Door_Closed",
			"Sprite" : "object-door_kin_closed.png",
			"Description" : "A steel door. Closed.",
			"Opaque" : true,
			"Pulse" : {
				"Receive" : true
			},
			"Permissions" : [ "Can_Enter_Fab" ],
            "Path Cost" : 100,
            "OpenType" : "Kin_Door_Open"
		},
		{
			"Name" : "Magnetic Door",
			"ObjectType" : "Kin_Door_Open",
			"Sprite" : "object-door_kin_open.png",
			"LuaEvents" : [
                { "Event" : "OnPulseReceived", "Script" : "Core.Objects.Door_OnPulseReceived" }
			],
			"Description" : "A steel door. Open.",
			"Pulse" : {
				"Receive" : true
			}
		},
		{
			"Name" : "Barred Door",
			"ObjectType" : "Elec_Door_Closed",
			"Sprite" : "object-door-electric-closed.png",
			"Description" : "A steel door. Closed.",
			"Opaque" : true,
			"Pulse" : {
				"Receive" : true
			},
            "Permissions" : [ "Nope" ],
            "Path Cost" : 100,
            "OpenType" : "Elec_Door_Open"
		},
		{
			"Name" : "Barred Door",
			"ObjectType" : "Elec_Door_Open",
			"Sprite" : "object-door-electric-open.png",
			"Description" : "A steel door. Open.",
			"Pulse" : {
				"Receive" : true
			}
		},
        {
            "Name" : "Closed Door",
            "ObjectType" : "Home_Door_Closed",
            "Sprite" : "object-door-electric-closed.png",
            "Description" : "A closed steel door. There is a slot beside it on the wall.",
            "LuaEvents" : [
                { "Event" : "OnInteract", "Script" : "Core.Objects.Interact_HomeDoor" }
            ],
            "Opaque" : true,
            "Path Cost" : 100,
            "Display In Editor" : false,
            "Permissions" : [ "Nope" ],
            "OpenType" : "Home_Door_Open"
        },
        {
            "Name" : "Open Door",
            "ObjectType" : "Home_Door_Open",
            "Sprite" : "object-door-electric-open.png",
            "Description" : "An open steel door. There is a slot beside it on the wall.",
            "Display In Editor" : false
        },
        {
            "Name" : "Closed Door",
            "ObjectType" : "Gold_Door_Closed",
            "Sprite" : "object-door_gold_closed.png",
            "Description" : "A closed gold door.",
            "Opaque" : true,
            "Path Cost" : 100,
            "Permissions" : [ "Sonar_Complete" ],
            "OpenType" : "Gold_Door_Open"
        },
        {
            "Name" : "Open Door",
            "ObjectType" : "Gold_Door_Open",
            "Sprite" : "object-door_gold_open.png",
            "Description" : "An open gold door."
        },
		{
			"Name" : "Switch",
			"ObjectType" : "Switch_On",
			"Sprite" : "object-switch_on.png",
			"Description" : "A lever. It is set to the \"ON\" position.",
			"LuaEvents" : [
                { "Event" : "OnInteract", "Script" : "Core.Objects.Interact_Switch" }
			],
			"Pulse" : {
				"Send" : true
			}
		},
		{
			"Name" : "Switch",
			"ObjectType" : "Switch_Off",
			"Sprite" : "object-switch_off.png",
			"Description" : "A lever. It is set to the \"OFF\" position.",
			"LuaEvents" : [
				{ "Event" : "OnInteract", "Script" : "Core.Objects.Interact_Switch" }
			],
			"Pulse" : {
				"Send" : true
			}
		},
        {
            "Name" : "Bed",
            "ObjectType" : "Bed",
            "Sprite" : "object-bed_small.png",
            "Render Layer" : "Back",
            "Description" : "Someone's bed."
        },
        {
            "Name" : "Sign",
            "ObjectType" : "Sign_House",
            "Sprite" : "object-sign.png",
            "Description" : "A sign.",
            "Render Layer" : "Back"
        },
        {
            "Name" : "Bed Roll",
            "ObjectType" : "Bed_Roll",
            "Sprite" : "object-bedroll.png",
            "Render Layer" : "Back",
            "Description" : "A portable sleeping spot."
        },
        {
            "Name" : "Brazier",
            "ObjectType" : "Brazier",
            "Sprite" : "object-brazier.png",
            "Light" : 4,
            "Render Layer" : "Back",
            "Description" : "A large braier filled with a flammable ore and incense. It burns brightly."
        },
        {
            "Name" : "Terminal",
            "ObjectType" : "Terminal_On",
			"LuaEvents" : [
                { "Event" : "OnInteract", "Script" : "Core.Objects.Interact_Terminal" }
			],
            "Sprite" : "object-terminal_on.png",
            "Description" : "A computer terminal. Its screen flashes brightly with text."
        },
        {
            "Name" : "Terminal",
            "ObjectType" : "Terminal_Off",
			"LuaEvents" : [
                { "Event" : "OnInteract", "Script" : "Core.Objects.Interact_Terminal" }
			],
            "Sprite" : "object-terminal_off.png",
            "Description" : "A computer terminal. It appears to be off."
        },
        {
            "Name" : "Statue",
            "ObjectType" : "Statue",
            "Sprite" : "object-statue.png",
            "Physics" : "Solid",
            "Render Layer" : "Front",
            "Description" : "A faceless statue made of solid gold. It appears to be praying.",
			"Opaque" : true
        },
        {
            "Name" : "Broken Statue",
            "ObjectType" : "Statue_Broken",
            "Sprite" : "object-statue_broken.png",
            "Physics" : "Solid",
            "Render Layer" : "Front",
            "Description" : "A faceless statue made of solid gold. It was broken."
        },
        {
            "Name" : "Curious Crystal",
            "ObjectType" : "Crystal",
            "Sprite" : "object-crystal_on.png",
            "Physics" : "Solid",
            "Light" : 1,
            "Render Layer" : "Front",
            "Description" : "What made such a curious structure? What could it do?"
        },
		{
            "Name" : "Surface Crystal",
            "ObjectType" : "Crystal_Surface",
			"LuaEvents" : [
                { "Event" : "OnInteract", "Script" : "Core.Objects.OnInteract_SurfaceTele" }
			],
            "Sprite" : "object-crystal_on.png",
			"Physics" : "Solid",
            "Light" : 1,
            "Render Layer" : "Front",
            "Description" : "A large green crystal that seems to float in place. It will likely take you to the surface."
        },
        {
            "Name" : "Bookshelf",
            "ObjectType" : "Bookshelf",
            "Sprite" : "object-bookshelf.png",
            "Physics" : "Solid",
            "Render Layer" : "Front",
            "Opaque" : true,
            "Description" : "A shelf containing several pieces of literature."
        },
        {
            "Name" : "Burnt Bookshelf",
            "ObjectType" : "Bookshelf_Burnt",
            "Sprite" : "object-bookshelf_burnt.png",
            "Physics" : "Solid",
            "Render Layer" : "Front",
            "Description" : "A shelf that contained literature. It is burnt, and the books within are illegible."
        },
		{
			"Name" : "Empty Bookshelf",
			"ObjectType" : "Bookshelf_Empty",
			"Sprite" : "object-bookshelf_empty.png",
			"Physics" : "Solid",
			"Render Layer" : "Front",
            "Opaque" : true,
			"Description" : "This shelf once contained pieces of literature."
		},
        {
            "Name" : "Cryopod",
            "ObjectType" : "Cryopod_Closed",
            "Sprite" : "object-cryopod_closed.png",
            "Physics" : "Solid",
			"LuaEvents" : [
                { "Event" : "OnInteract", "Script" : "Core.Objects.Interact_Cryopod" }
			],
            "Opaque" : true,
            "Render Layer" : "Front",
            "Description" : "A pod made to house people in a deep sleep during space travel."
        },
        {
            "Name" : "Cryopod",
            "ObjectType" : "Cryopod_Open",
            "Sprite" : "object-cryopod_open.png",
            "Physics" : "Solid",
            "Opaque" : true,
            "Render Layer" : "Front",
            "Description" : "A pod made to house people in a deep sleep during space travel."
        },
        {
            "Name" : "Cloning Chamber",
            "ObjectType" : "CloningChamber_Empty",
            "Sprite" : "object-cloningchamber.png",
            "Physics" : "Solid",
            "Opaque" : true,
            "Render Layer" : "Front",
            "Description" : "A large vat filled with a viscous green liquid. Its empty chamber is used to clone creatures."
        },
        {
            "Name" : "Cloning Chamber",
            "ObjectType" : "CloningChamber_Full",
            "Sprite" : "object-cloningchamber_full.png",
            "Physics" : "Solid",
            "Opaque" : true,
            "Render Layer" : "Front",
            "Description" : "A large vat filled with a viscous green liquid. It contains some kind of being."
        },
        {
            "Name" : "Stone",
            "ObjectType" : "Stone",
            "Sprite" : "object-stone.png",
            "Render Layer" : "Back",
            "Description" : "A stone protruding from the earth."
        },
        {
            "Name" : "Web",
            "ObjectType" : "Web",
			"Path Cost" : 3,
            "Sprite" : "object-web.png",
            "Render Layer" : "Back",
			"LuaEvents" : [
                { "Event" : "OnEntityEnter", "Script" : "Core.Objects.OnEnter_Web" },
                { "Event" : "OnEntityExit", "Script" : "Core.Objects.OnExit_Web" }
			],
            "Description" : "A strongly woven web, probably made by a large arachnid."
        },
        {
            "Name" : "Anvil",
            "ObjectType" : "Anvil",
            "Sprite" : "object-anvil.png",
            "Physics" : "Solid",
            "Render Layer" : "Front",
            "Description" : "A tool used by blacksmiths and other metal workers."
        },
        {
            "Name" : "Ore",
            "ObjectType" : "Ore",
            "Sprite" : "object-ore.png",
            "Physics" : "Solid",
            "Render Layer" : "Front",
            "Description" : "A tool used by blacksmiths and other metal workers."
        },
        {
        	"Name" : "Stair Lock",
        	"ObjectType" : "Stair_Lock",
        	"Sprite" : "object-stairlock.png",
        	"Physics" : "Solid",
			"LuaEvents" : [
                { "Event" : "OnInteract", "Script" : "Core.Objects.Interact_Stairlock" }
			],
        	"Render Layer" : "Front",
        	"Description" : "A blocking stone, heavy and chained. It is used to cover staircases.",
			"Opaque" : true,
            "Display In Editor" : false
        },
		{
			"Name" : "Portal",
			"ObjectType" : "Portal",
			"Sprite" : "object-portal.png",
			"LuaEvents" : [
                { "Event" : "OnInteract", "Script" : "Core.Objects.Interact_Portal" }
			],
			"Description" : "A translucent portal.",
			"Render Layer" : "Front"
		},
        {
            "Name" : "Fence",
            "ObjectType" : "Fence",
            "Sprite" : "object-fence.png",
            "Physics" : "Solid",
            "Render Layer" : "Front",
			"Autotile" : true,
            "Description" : "A sturdy wood fence."
        },
        {
            "Name" : "Bars",
            "ObjectType" : "Bars",
            "Sprite" : "object-bars.png",
            "Physics" : "Solid",
            "Render Layer" : "Front",
			"Autotile" : true,
            "Description" : "Thick bars made of rusted metal."
        },
        {
            "Name" : "Headstone",
            "ObjectType" : "Headstone",
            "Sprite" : "object-gravestone.png",
            "Physics" : "Solid",
            "Render Layer" : "Front",
            "Description" : "A headstone for a deceased person."
        },
        {
            "Name" : "Grave",
            "ObjectType" : "Grave",
            "Sprite" : "object-grave.png",
            "LuaEvents" : [
                { "Event" : "OnInteract", "Script" : "Core.Objects.Interact_Grave" }
			],
            "Render Layer" : "Back",
            "Description" : ""
        },
        {
            "Name" : "Open Grave",
            "ObjectType" : "Grave_Dug",
            "Sprite" : "object-grave_dug.png",
            "Render Layer" : "Back",
            "Description" : ""
        },
        {
            "Name" : "Pine Tree",
            "ObjectType" : "Tree_Pine",
            "Sprite" : "object-tree_pine.png",
            "Physics" : "Solid",
            "Render Layer" : "Front",
            "Description" : "A sturdy pine tree.",
			"Opaque" : true,
            "Display In Editor" : false
        },
		{
            "Name" : "Tall Grass",
            "ObjectType" : "Tall_Grass",
            "Sprite" : "object-grass.png",
            "Render Layer" : "Front",
            "Description" : "Tall grass, perfect for hiding."
        },
        {
            "Name" : "Robotic Frame",
            "ObjectType" : "Robot_Frame",
            "Sprite" : "object-robot.png",
			"Physics" : "Solid",
			"Render Layer" : "Front",
            "Description" : "An empty robotic chasis. It requires an AI Core to interact with."
        },
		{
			"Name" : "Wire",
			"ObjectType" : "Wire",
			"Sprite" : "object-wire.png",
			"Render Layer" : "Back",
			"Autotile" : true,
			"Description" : "A strand of electrical wire.",
			"Pulse" : {
				"Send" : true,
				"Receive" : true
			}
		},
		{
			"Name" : "Hidden Wire",
			"ObjectType" : "Wire_Hidden",
			"Sprite" : "object-empty.png",
			"Render Layer" : "Back",
			"Description" : "",
			"Pulse" : {
				"Send" : true,
				"Receive" : true
			}
		},
		{
			"Name" : "Battery",
			"ObjectType" : "Battery",
			"Sprite" : "object-battery.png",
			"Physics" : "Solid",
            "Opaque" : true,
			"Render Layer" : "Front",
			"Description" : "Storage for electrical power."
		},
		{
			"Name" : "Track",
			"ObjectType" : "Track",
			"Sprite" : "object-track.png",
			"Render Layer" : "Back",
			"Autotile" : true,
			"Description" : ""
		},
		{
			"Name" : "Minecart",
			"ObjectType" : "Minecart",
			"Sprite" : "object-minecart.png",
			"Render Layer" : "Front",
			"Physics" : "Solid",
            "Opaque" : true,
			"Description" : ""
		},
		{
			"Name" : "Spike Trap",
			"ObjectType" : "Trap_Spike",
			"Sprite" : "object-trap_spike.png",
			"Render Layer" : "Back",
			"LuaEvents" : [
                { "Event" : "OnEntityEnter", "Script" : "Core.Objects.OnEnter_SpikeTrap" }
			],
			"Description" : "A floor panel with holes. You can see a thin coating of blood."
		},
		{
			"Name" : "Poison Trap",
			"ObjectType" : "Trap_Poison",
			"Sprite" : "object-trap_gas.png",
			"Render Layer" : "Back",
			"LuaEvents" : [
				{ "Event" : "OnEntityEnter", "Script" : "Core.Objects.OnEnter_PoisonTrap" }
			],
			"Description" : "A floor panel with holes. There is a foul smell coming from it."
		},
		{
			"Name" : "Blinding Gas Trap",
			"ObjectType" : "Trap_Gas",
			"Sprite" : "object-trap_gas.png",
			"Render Layer" : "Back",
			"LuaEvents" : [
				{ "Event" : "OnEntityEnter", "Script" : "Core.Objects.OnEnter_BlindTrap" }
			],
			"Description" : "A floor panel with holes. There is a foul smell coming from it."
		},
		{
			"Name" : "Pressure Plate",
			"ObjectType" : "PressurePlate",
			"Sprite" : "object-pressureplate.png",
			"LuaEvents" : [
                { "Event" : "OnEntityEnter", "Script" : "Core.Objects.OnEnter_PressurePlate" },
                { "Event" : "OnEntityExit", "Script" : "Core.Objects.OnExit_PressurePlate" }
			],
			"Description" : "A raised piece of floor.",
			"Render Layer" : "Back",
			"Pulse" : {
				"Send" : true
			}
		},
		{
			"Name" : "Signal Light",
			"ObjectType" : "Light_On",
			"Sprite" : "object-light_on.png",
			"LuaEvents" : [
                { "Event" : "OnPulseReceived", "Script" : "Core.Objects.Light_PulseReceived" }
			],
			"Description" : "",
			"Pulse" : {
				"Receive" : true
			},
            "Display In Editor" : false
		},
		{
			"Name" : "Signal Light",
			"ObjectType" : "Light_Off",
			"Sprite" : "object-light_off.png",
			"LuaEvents" : [
                { "Event" : "OnPulseReceived", "Script" : "Core.Objects.Light_PulseReceived" }
			],
			"Description" : "",
			"Pulse" : {
				"Receive" : true
			},
            "Display In Editor" : false
		},
		{
			"Name" : "Coffin",
			"ObjectType" : "Coffin",
			"Sprite" : "object-coffin.png",
			"Physics" : "Solid",
            "Opaque" : true,
			"Render Layer" : "Front",
			"Description" : "Storage for the dead."
		},
		{
			"Name" : "Forge",
			"ObjectType" : "Forge",
			"Sprite" : "object-forge.png",
			"Physics" : "Solid",
            "Opaque" : true,
			"Render Layer" : "Front",
			"Description" : "A hearth used for heating metals for blacksmithing."
		},
		{
			"Name" : "Polarity Reverser",
			"ObjectType" : "PolReverse",
			"Sprite" : "object-reverse.png",
			"Description" : "Reverses the polarity of a wire's signal.",
			"Render Layer" : "Back",
			"Pulse" : {
				"Send" : true,
				"Receive" : true,
				"Reverse" : true
			}
		},
		{
			"Name" : "Pit",
			"ObjectType" : "Spike_Down",
			"Sprite" : "object-spike_down.png",
			"Description" : "",
			"Path Cost" : 10,
			"Render Layer" : "Back",
			"LuaEvents" : [
                { "Event" : "OnTurn", "Script" : "Core.Objects.OnTurn_Spike" }
			]
		},
		{
			"Name" : "Spike",
			"ObjectType" : "Spike_Up",
			"Sprite" : "object-spike_up.png",
			"Description" : "",
            "Render Layer" : "Back",
			"LuaEvents" : [
                { "Event" : "OnTurn", "Script" : "Core.Objects.OnTurn_Spike" }
			]
		}
    ]
}